advanced_radiomics/__init__.py
advanced_radiomics/_version.py
advanced_radiomics/analysis.py
advanced_radiomics/extract.py
advanced_radiomics/visualization.py
advanced_radiomics/tests/__init__.py
advanced_radiomics/tests/conftest.py
advanced_radiomics/tests/test_examples.py
advanced_radiomics-0.2.1.dist-info/AUTHORS.rst
advanced_radiomics-0.2.1.dist-info/LICENSE
advanced_radiomics-0.2.1.dist-info/METADATA
advanced_radiomics-0.2.1.dist-info/WHEEL
advanced_radiomics-0.2.1.dist-info/entry_points.txt
advanced_radiomics-0.2.1.dist-info/top_level.txt
advanced_radiomics-0.2.1.dist-info/RECORD
