Metadata-Version: 2.1
Name: advanced-radiomics
Version: 0.2.1
Summary: Advanced Radiomics Functions.
Home-page: https://github.com/FelipeAugustoMachado/advanced-radiomics
Author: Machado, F. A. M.; Castaldoni, R. C. 
Author-email: f.a.moraes.machado@gmail.com
License: BSD (3-clause)
Platform: UNKNOWN
Classifier: Development Status :: 2 - Pre-Alpha
Classifier: Natural Language :: English
Classifier: Programming Language :: Python :: 3
Requires-Python: >=3.6
License-File: LICENSE
License-File: AUTHORS.rst
Requires-Dist: numpy
Requires-Dist: pandas
Requires-Dist: SimpleITK
Requires-Dist: pyradiomics
Requires-Dist: seaborn
Requires-Dist: matplotlib
Requires-Dist: sklearn
Requires-Dist: scipy
Requires-Dist: opencv-python
